sovai_cluster/__init__.py
sovai_cluster/clustering.py
sovai_cluster/data_processing.py
sovai_cluster/setup_structure.py
sovai_cluster/utils.py
sovai_cluster/visualization.py
sovai_cluster-0.1.2.dist-info/METADATA
sovai_cluster-0.1.2.dist-info/WHEEL
sovai_cluster-0.1.2.dist-info/RECORD
